bittensor/__init__.py
bittensor/__main__.py
bittensor/core/__init__.py
bittensor/core/async_subtensor.py
bittensor/core/axon.py
bittensor/core/config.py
bittensor/core/dendrite.py
bittensor/core/errors.py
bittensor/core/metagraph.py
bittensor/core/settings.py
bittensor/core/stream.py
bittensor/core/subtensor.py
bittensor/core/synapse.py
bittensor/core/tensor.py
bittensor/core/threadpool.py
bittensor/core/types.py
bittensor/core/chain_data/__init__.py
bittensor/core/chain_data/axon_info.py
bittensor/core/chain_data/chain_identity.py
bittensor/core/chain_data/crowdloan_info.py
bittensor/core/chain_data/delegate_info.py
bittensor/core/chain_data/delegate_info_lite.py
bittensor/core/chain_data/dynamic_info.py
bittensor/core/chain_data/info_base.py
bittensor/core/chain_data/ip_info.py
bittensor/core/chain_data/metagraph_info.py
bittensor/core/chain_data/neuron_info.py
bittensor/core/chain_data/neuron_info_lite.py
bittensor/core/chain_data/prometheus_info.py
bittensor/core/chain_data/proposal_vote_data.py
bittensor/core/chain_data/proxy.py
bittensor/core/chain_data/root_claim.py
bittensor/core/chain_data/scheduled_coldkey_swap_info.py
bittensor/core/chain_data/sim_swap.py
bittensor/core/chain_data/stake_info.py
bittensor/core/chain_data/subnet_hyperparameters.py
bittensor/core/chain_data/subnet_identity.py
bittensor/core/chain_data/subnet_info.py
bittensor/core/chain_data/subnet_state.py
bittensor/core/chain_data/utils.py
bittensor/core/chain_data/weight_commit_info.py
bittensor/core/extrinsics/__init__.py
bittensor/core/extrinsics/children.py
bittensor/core/extrinsics/crowdloan.py
bittensor/core/extrinsics/liquidity.py
bittensor/core/extrinsics/mev_shield.py
bittensor/core/extrinsics/move_stake.py
bittensor/core/extrinsics/proxy.py
bittensor/core/extrinsics/registration.py
bittensor/core/extrinsics/root.py
bittensor/core/extrinsics/serving.py
bittensor/core/extrinsics/staking.py
bittensor/core/extrinsics/start_call.py
bittensor/core/extrinsics/sudo.py
bittensor-10.1.0.dist-info/licenses/LICENSE
bittensor-10.1.0.dist-info/METADATA
bittensor-10.1.0.dist-info/WHEEL
bittensor-10.1.0.dist-info/top_level.txt
bittensor-10.1.0.dist-info/RECORD
