Metadata-Version: 2.4
Name: bittensor
Version: 10.1.0
Summary: Bittensor SDK
Author: bittensor.com
License: The MIT License (MIT)
Project-URL: homepage, https://github.com/opentensor/bittensor
Project-URL: Repository, https://github.com/opentensor/bittensor
Requires-Python: <3.15,>=3.10
License-File: LICENSE
Requires-Dist: wheel
Requires-Dist: setuptools~=70.0
Requires-Dist: aiohttp<4.0,>=3.9
Requires-Dist: asyncstdlib~=3.13.0
Requires-Dist: colorama~=0.4.6
Requires-Dist: fastapi>=0.110.1
Requires-Dist: munch>=4.0.0
Requires-Dist: numpy<3.0.0,>=2.0.1
Requires-Dist: msgpack-numpy-opentensor~=0.5
Requires-Dist: netaddr==1.3.0
Requires-Dist: packaging
Requires-Dist: python-statemachine~=2.1
Requires-Dist: pycryptodome<4.0.0,>=3.18.0
Requires-Dist: pyyaml>=6.0
Requires-Dist: retry==0.9.2
Requires-Dist: requests<3.0,>=2.0.0
Requires-Dist: pydantic<3,>=2.3
Requires-Dist: scalecodec==1.2.12
Requires-Dist: uvicorn
Requires-Dist: bittensor-drand<2.0.0,>=1.2.0
Requires-Dist: bittensor-wallet<5.0,>=4.0.0
Requires-Dist: async-substrate-interface>=1.5.15
Provides-Extra: dev
Requires-Dist: pytest==8.3.5; extra == "dev"
Requires-Dist: pytest-asyncio==0.26.0; extra == "dev"
Requires-Dist: pytest-mock==3.14.0; extra == "dev"
Requires-Dist: pytest-split==0.10.0; extra == "dev"
Requires-Dist: pytest-xdist==3.6.1; extra == "dev"
Requires-Dist: pytest-rerunfailures==10.2; extra == "dev"
Requires-Dist: coveralls==3.3.1; extra == "dev"
Requires-Dist: pytest-cov==4.0.0; extra == "dev"
Requires-Dist: ddt==1.6.0; extra == "dev"
Requires-Dist: hypothesis==6.81.1; extra == "dev"
Requires-Dist: flake8==7.0.0; extra == "dev"
Requires-Dist: mypy==1.8.0; extra == "dev"
Requires-Dist: types-retry==0.9.9.4; extra == "dev"
Requires-Dist: freezegun==1.5.0; extra == "dev"
Requires-Dist: httpx==0.27.0; extra == "dev"
Requires-Dist: ruff==0.11.5; extra == "dev"
Requires-Dist: aioresponses==0.7.6; extra == "dev"
Requires-Dist: factory-boy==3.3.0; extra == "dev"
Requires-Dist: types-requests; extra == "dev"
Provides-Extra: torch
Requires-Dist: torch<3.0,>=1.13.1; extra == "torch"
Provides-Extra: cli
Requires-Dist: bittensor-cli>=9.16.0; extra == "cli"
Dynamic: license-file
